ambusoetl/__init__.py
ambusoetl/extract.py
ambusoetl/load.py
ambusoetl/main.py
ambusoetl/transform.py
ambusoetl-0.1.0.dist-info/METADATA
ambusoetl-0.1.0.dist-info/WHEEL
ambusoetl-0.1.0.dist-info/top_level.txt
ambusoetl-0.1.0.dist-info/RECORD
