Metadata-Version: 2.4
Name: ambusoetl
Version: 0.1.0
Summary: ambusoetl, an end-to-end ETL (Extract, Transform, Load) pipeline development package using pandas, requests, psycopg2-binary
Author-email: Dismas Mike <dismasmik3@gmail.com>
License-Expression: MIT
Requires-Python: >=3.7
Requires-Dist: pandas
Requires-Dist: requests
Requires-Dist: sqlalchemy
Requires-Dist: psycopg2-binary
Requires-Dist: numpy
